pbiapi/__init__.py
pbiapi/pbiapi.py
pbiapi/utils.py
pbiapi-0.2.1.dist-info/LICENSE
pbiapi-0.2.1.dist-info/WHEEL
pbiapi-0.2.1.dist-info/METADATA
pbiapi-0.2.1.dist-info/RECORD
