Metadata-Version: 2.1
Name: pbiapi
Version: 0.2.1
Summary: A Python library for working with the Power BI API
Home-page: https://github.com/scottmelhop/PowerBI-API-Python
Author: Scott Melhop
Author-email: scott.melhop@cognite.com
Requires-Python: >=3.7,<4.0
Classifier: License :: OSI Approved :: MIT License
Classifier: Operating System :: OS Independent
Classifier: Programming Language :: Python :: 3
Classifier: Programming Language :: Python :: 3.7
Classifier: Programming Language :: Python :: 3.8
Classifier: Programming Language :: Python :: 3.9
Requires-Dist: requests (>=2.23.0,<3.0.0)
Project-URL: Repository, https://github.com/scottmelhop/PowerBI-API-Python
